{"nodes": [{"id": "notification", "label": "notification.py", "file_type": "code", "source_file": "backend/app/models/notification.py", "source_location": "L1"}, {"id": "notification_notification", "label": "Notification", "file_type": "code", "source_file": "backend/app/models/notification.py", "source_location": "L13"}, {"id": "notification_rationale_1", "label": "Notification model \u2014 notifications for users and agents.", "file_type": "rationale", "source_file": "backend/app/models/notification.py", "source_location": "L1"}, {"id": "notification_rationale_14", "label": "A notification delivered to a user or an agent.", "file_type": "rationale", "source_file": "backend/app/models/notification.py", "source_location": "L14"}], "edges": [{"source": "notification", "target": "uuid", "relation": "imports", "confidence": "EXTRACTED", "source_file": "backend/app/models/notification.py", "source_location": "L3", "weight": 1.0}, {"source": "notification", "target": "datetime", "relation": "imports_from", "confidence": "EXTRACTED", "source_file": "backend/app/models/notification.py", "source_location": "L4", "weight": 1.0}, {"source": "notification", "target": "sqlalchemy", "relation": "imports_from", "confidence": "EXTRACTED", "source_file": "backend/app/models/notification.py", "source_location": "L6", "weight": 1.0}, {"source": "notification", "target": "sqlalchemy_dialects_postgresql", "relation": "imports_from", "confidence": "EXTRACTED", "source_file": "backend/app/models/notification.py", "source_location": "L7", "weight": 1.0}, {"source": "notification", "target": "sqlalchemy_orm", "relation": "imports_from", "confidence": "EXTRACTED", "source_file": "backend/app/models/notification.py", "source_location": "L8", "weight": 1.0}, {"source": "notification", "target": "app_database", "relation": "imports_from", "confidence": "EXTRACTED", "source_file": "backend/app/models/notification.py", "source_location": "L10", "weight": 1.0}, {"source": "notification", "target": "notification_notification", "relation": "contains", "confidence": "EXTRACTED", "source_file": "backend/app/models/notification.py", "source_location": "L13", "weight": 1.0}, {"source": "notification_notification", "target": "base", "relation": "inherits", "confidence": "EXTRACTED", "source_file": "backend/app/models/notification.py", "source_location": "L13", "weight": 1.0}, {"source": "notification_rationale_1", "target": "notification", "relation": "rationale_for", "confidence": "EXTRACTED", "source_file": "backend/app/models/notification.py", "source_location": "L1", "weight": 1.0}, {"source": "notification_rationale_14", "target": "notification_notification", "relation": "rationale_for", "confidence": "EXTRACTED", "source_file": "backend/app/models/notification.py", "source_location": "L14", "weight": 1.0}], "hyperedges": []}