{"nodes": [{"id": "backend_app_services_text_extractor_py", "label": "text_extractor.py", "file_type": "code", "source_file": "backend/app/services/text_extractor.py", "source_location": "L1"}, {"id": "text_extractor_needs_extraction", "label": "needs_extraction()", "file_type": "code", "source_file": "backend/app/services/text_extractor.py", "source_location": "L21"}, {"id": "text_extractor_extract_text", "label": "extract_text()", "file_type": "code", "source_file": "backend/app/services/text_extractor.py", "source_location": "L27"}, {"id": "text_extractor_save_extracted_text", "label": "save_extracted_text()", "file_type": "code", "source_file": "backend/app/services/text_extractor.py", "source_location": "L50"}, {"id": "text_extractor_extract_pdf", "label": "_extract_pdf()", "file_type": "code", "source_file": "backend/app/services/text_extractor.py", "source_location": "L66"}, {"id": "text_extractor_extract_docx", "label": "_extract_docx()", "file_type": "code", "source_file": "backend/app/services/text_extractor.py", "source_location": "L91"}, {"id": "text_extractor_extract_xlsx", "label": "_extract_xlsx()", "file_type": "code", "source_file": "backend/app/services/text_extractor.py", "source_location": "L124"}, {"id": "text_extractor_extract_pptx", "label": "_extract_pptx()", "file_type": "code", "source_file": "backend/app/services/text_extractor.py", "source_location": "L146"}, {"id": "text_extractor_rationale_1", "label": "Extract text from common office file formats.  Supports: PDF, DOCX, XLSX, PPTX,", "file_type": "rationale", "source_file": "backend/app/services/text_extractor.py", "source_location": "L1"}, {"id": "text_extractor_rationale_22", "label": "Check if a file needs text extraction.", "file_type": "rationale", "source_file": "backend/app/services/text_extractor.py", "source_location": "L22"}, {"id": "text_extractor_rationale_28", "label": "Extract text from a binary file.          Returns extracted text string, or None", "file_type": "rationale", "source_file": "backend/app/services/text_extractor.py", "source_location": "L28"}, {"id": "text_extractor_rationale_51", "label": "Extract text and save as a companion .txt file.          For example: report.pdf", "file_type": "rationale", "source_file": "backend/app/services/text_extractor.py", "source_location": "L51"}, {"id": "text_extractor_rationale_67", "label": "Extract text from PDF using pdfplumber.", "file_type": "rationale", "source_file": "backend/app/services/text_extractor.py", "source_location": "L67"}, {"id": "text_extractor_rationale_92", "label": "Extract text from DOCX using python-docx.", "file_type": "rationale", "source_file": "backend/app/services/text_extractor.py", "source_location": "L92"}, {"id": "text_extractor_rationale_125", "label": "Extract text from XLSX using openpyxl.", "file_type": "rationale", "source_file": "backend/app/services/text_extractor.py", "source_location": "L125"}, {"id": "text_extractor_rationale_147", "label": "Extract text from PPTX using python-pptx.", "file_type": "rationale", "source_file": "backend/app/services/text_extractor.py", "source_location": "L147"}], "edges": [{"source": "backend_app_services_text_extractor_py", "target": "io", "relation": "imports", "confidence": "EXTRACTED", "source_file": "backend/app/services/text_extractor.py", "source_location": "L7", "weight": 1.0}, {"source": "backend_app_services_text_extractor_py", "target": "pathlib", "relation": "imports_from", "confidence": "EXTRACTED", "source_file": "backend/app/services/text_extractor.py", "source_location": "L8", "weight": 1.0}, {"source": "backend_app_services_text_extractor_py", "target": "loguru", "relation": "imports_from", "confidence": "EXTRACTED", "source_file": "backend/app/services/text_extractor.py", "source_location": "L10", "weight": 1.0}, {"source": "backend_app_services_text_extractor_py", "target": "text_extractor_needs_extraction", "relation": "contains", "confidence": "EXTRACTED", "source_file": "backend/app/services/text_extractor.py", "source_location": "L21", "weight": 1.0}, {"source": "backend_app_services_text_extractor_py", "target": "text_extractor_extract_text", "relation": "contains", "confidence": "EXTRACTED", "source_file": "backend/app/services/text_extractor.py", "source_location": "L27", "weight": 1.0}, {"source": "backend_app_services_text_extractor_py", "target": "text_extractor_save_extracted_text", "relation": "contains", "confidence": "EXTRACTED", "source_file": "backend/app/services/text_extractor.py", "source_location": "L50", "weight": 1.0}, {"source": "backend_app_services_text_extractor_py", "target": "text_extractor_extract_pdf", "relation": "contains", "confidence": "EXTRACTED", "source_file": "backend/app/services/text_extractor.py", "source_location": "L66", "weight": 1.0}, {"source": "backend_app_services_text_extractor_py", "target": "text_extractor_extract_docx", "relation": "contains", "confidence": "EXTRACTED", "source_file": "backend/app/services/text_extractor.py", "source_location": "L91", "weight": 1.0}, {"source": "backend_app_services_text_extractor_py", "target": "text_extractor_extract_xlsx", "relation": "contains", "confidence": "EXTRACTED", "source_file": "backend/app/services/text_extractor.py", "source_location": "L124", "weight": 1.0}, {"source": "backend_app_services_text_extractor_py", "target": "text_extractor_extract_pptx", "relation": "contains", "confidence": "EXTRACTED", "source_file": "backend/app/services/text_extractor.py", "source_location": "L146", "weight": 1.0}, {"source": "text_extractor_extract_text", "target": "text_extractor_extract_pdf", "relation": "calls", "confidence": "EXTRACTED", "source_file": "backend/app/services/text_extractor.py", "source_location": "L36", "weight": 1.0}, {"source": "text_extractor_extract_text", "target": "text_extractor_extract_docx", "relation": "calls", "confidence": "EXTRACTED", "source_file": "backend/app/services/text_extractor.py", "source_location": "L38", "weight": 1.0}, {"source": "text_extractor_extract_text", "target": "text_extractor_extract_xlsx", "relation": "calls", "confidence": "EXTRACTED", "source_file": "backend/app/services/text_extractor.py", "source_location": "L40", "weight": 1.0}, {"source": "text_extractor_extract_text", "target": "text_extractor_extract_pptx", "relation": "calls", "confidence": "EXTRACTED", "source_file": "backend/app/services/text_extractor.py", "source_location": "L42", "weight": 1.0}, {"source": "text_extractor_save_extracted_text", "target": "text_extractor_extract_text", "relation": "calls", "confidence": "EXTRACTED", "source_file": "backend/app/services/text_extractor.py", "source_location": "L56", "weight": 1.0}, {"source": "text_extractor_extract_pdf", "target": "text_extractor_extract_text", "relation": "calls", "confidence": "EXTRACTED", "source_file": "backend/app/services/text_extractor.py", "source_location": "L73", "weight": 1.0}, {"source": "text_extractor_rationale_1", "target": "backend_app_services_text_extractor_py", "relation": "rationale_for", "confidence": "EXTRACTED", "source_file": "backend/app/services/text_extractor.py", "source_location": "L1", "weight": 1.0}, {"source": "text_extractor_rationale_22", "target": "text_extractor_needs_extraction", "relation": "rationale_for", "confidence": "EXTRACTED", "source_file": "backend/app/services/text_extractor.py", "source_location": "L22", "weight": 1.0}, {"source": "text_extractor_rationale_28", "target": "text_extractor_extract_text", "relation": "rationale_for", "confidence": "EXTRACTED", "source_file": "backend/app/services/text_extractor.py", "source_location": "L28", "weight": 1.0}, {"source": "text_extractor_rationale_51", "target": "text_extractor_save_extracted_text", "relation": "rationale_for", "confidence": "EXTRACTED", "source_file": "backend/app/services/text_extractor.py", "source_location": "L51", "weight": 1.0}, {"source": "text_extractor_rationale_67", "target": "text_extractor_extract_pdf", "relation": "rationale_for", "confidence": "EXTRACTED", "source_file": "backend/app/services/text_extractor.py", "source_location": "L67", "weight": 1.0}, {"source": "text_extractor_rationale_92", "target": "text_extractor_extract_docx", "relation": "rationale_for", "confidence": "EXTRACTED", "source_file": "backend/app/services/text_extractor.py", "source_location": "L92", "weight": 1.0}, {"source": "text_extractor_rationale_125", "target": "text_extractor_extract_xlsx", "relation": "rationale_for", "confidence": "EXTRACTED", "source_file": "backend/app/services/text_extractor.py", "source_location": "L125", "weight": 1.0}, {"source": "text_extractor_rationale_147", "target": "text_extractor_extract_pptx", "relation": "rationale_for", "confidence": "EXTRACTED", "source_file": "backend/app/services/text_extractor.py", "source_location": "L147", "weight": 1.0}], "raw_calls": [{"caller_nid": "text_extractor_needs_extraction", "callee": "lower", "source_file": "backend/app/services/text_extractor.py", "source_location": "L23"}, {"caller_nid": "text_extractor_needs_extraction", "callee": "Path", "source_file": "backend/app/services/text_extractor.py", "source_location": "L23"}, {"caller_nid": "text_extractor_extract_text", "callee": "lower", "source_file": "backend/app/services/text_extractor.py", "source_location": "L32"}, {"caller_nid": "text_extractor_extract_text", "callee": "Path", "source_file": "backend/app/services/text_extractor.py", "source_location": "L32"}, {"caller_nid": "text_extractor_extract_text", "callee": "error", "source_file": "backend/app/services/text_extractor.py", "source_location": "L44"}, {"caller_nid": "text_extractor_save_extracted_text", "callee": "strip", "source_file": "backend/app/services/text_extractor.py", "source_location": "L57"}, {"caller_nid": "text_extractor_save_extracted_text", "callee": "write_text", "source_file": "backend/app/services/text_extractor.py", "source_location": "L61"}, {"caller_nid": "text_extractor_save_extracted_text", "callee": "info", "source_file": "backend/app/services/text_extractor.py", "source_location": "L62"}, {"caller_nid": "text_extractor_save_extracted_text", "callee": "len", "source_file": "backend/app/services/text_extractor.py", "source_location": "L62"}, {"caller_nid": "text_extractor_extract_pdf", "callee": "open", "source_file": "backend/app/services/text_extractor.py", "source_location": "L71"}, {"caller_nid": "text_extractor_extract_pdf", "callee": "BytesIO", "source_file": "backend/app/services/text_extractor.py", "source_location": "L71"}, {"caller_nid": "text_extractor_extract_pdf", "callee": "enumerate", "source_file": "backend/app/services/text_extractor.py", "source_location": "L72"}, {"caller_nid": "text_extractor_extract_pdf", "callee": "strip", "source_file": "backend/app/services/text_extractor.py", "source_location": "L74"}, {"caller_nid": "text_extractor_extract_pdf", "callee": "append", "source_file": "backend/app/services/text_extractor.py", "source_location": "L75"}, {"caller_nid": "text_extractor_extract_pdf", "callee": "strip", "source_file": "backend/app/services/text_extractor.py", "source_location": "L75"}, {"caller_nid": "text_extractor_extract_pdf", "callee": "extract_tables", "source_file": "backend/app/services/text_extractor.py", "source_location": "L78"}, {"caller_nid": "text_extractor_extract_pdf", "callee": "strip", "source_file": "backend/app/services/text_extractor.py", "source_location": "L83"}, {"caller_nid": "text_extractor_extract_pdf", "callee": "str", "source_file": "backend/app/services/text_extractor.py", "source_location": "L83"}, {"caller_nid": "text_extractor_extract_pdf", "callee": "append", "source_file": "backend/app/services/text_extractor.py", "source_location": "L84"}, {"caller_nid": "text_extractor_extract_pdf", "callee": "join", "source_file": "backend/app/services/text_extractor.py", "source_location": "L84"}, {"caller_nid": "text_extractor_extract_pdf", "callee": "append", "source_file": "backend/app/services/text_extractor.py", "source_location": "L86"}, {"caller_nid": "text_extractor_extract_pdf", "callee": "join", "source_file": "backend/app/services/text_extractor.py", "source_location": "L86"}, {"caller_nid": "text_extractor_extract_pdf", "callee": "join", "source_file": "backend/app/services/text_extractor.py", "source_location": "L88"}, {"caller_nid": "text_extractor_extract_docx", "callee": "Document", "source_file": "backend/app/services/text_extractor.py", "source_location": "L95"}, {"caller_nid": "text_extractor_extract_docx", "callee": "BytesIO", "source_file": "backend/app/services/text_extractor.py", "source_location": "L95"}, {"caller_nid": "text_extractor_extract_docx", "callee": "strip", "source_file": "backend/app/services/text_extractor.py", "source_location": "L99"}, {"caller_nid": "text_extractor_extract_docx", "callee": "startswith", "source_file": "backend/app/services/text_extractor.py", "source_location": "L102"}, {"caller_nid": "text_extractor_extract_docx", "callee": "strip", "source_file": "backend/app/services/text_extractor.py", "source_location": "L103"}, {"caller_nid": "text_extractor_extract_docx", "callee": "replace", "source_file": "backend/app/services/text_extractor.py", "source_location": "L103"}, {"caller_nid": "text_extractor_extract_docx", "callee": "int", "source_file": "backend/app/services/text_extractor.py", "source_location": "L105"}, {"caller_nid": "text_extractor_extract_docx", "callee": "append", "source_file": "backend/app/services/text_extractor.py", "source_location": "L108"}, {"caller_nid": "text_extractor_extract_docx", "callee": "append", "source_file": "backend/app/services/text_extractor.py", "source_location": "L110"}, {"caller_nid": "text_extractor_extract_docx", "callee": "strip", "source_file": "backend/app/services/text_extractor.py", "source_location": "L116"}, {"caller_nid": "text_extractor_extract_docx", "callee": "append", "source_file": "backend/app/services/text_extractor.py", "source_location": "L117"}, {"caller_nid": "text_extractor_extract_docx", "callee": "join", "source_file": "backend/app/services/text_extractor.py", "source_location": "L117"}, {"caller_nid": "text_extractor_extract_docx", "callee": "append", "source_file": "backend/app/services/text_extractor.py", "source_location": "L119"}, {"caller_nid": "text_extractor_extract_docx", "callee": "join", "source_file": "backend/app/services/text_extractor.py", "source_location": "L119"}, {"caller_nid": "text_extractor_extract_docx", "callee": "join", "source_file": "backend/app/services/text_extractor.py", "source_location": "L121"}, {"caller_nid": "text_extractor_extract_xlsx", "callee": "load_workbook", "source_file": "backend/app/services/text_extractor.py", "source_location": "L128"}, {"caller_nid": "text_extractor_extract_xlsx", "callee": "BytesIO", "source_file": "backend/app/services/text_extractor.py", "source_location": "L128"}, {"caller_nid": "text_extractor_extract_xlsx", "callee": "iter_rows", "source_file": "backend/app/services/text_extractor.py", "source_location": "L134"}, {"caller_nid": "text_extractor_extract_xlsx", "callee": "str", "source_file": "backend/app/services/text_extractor.py", "source_location": "L135"}, {"caller_nid": "text_extractor_extract_xlsx", "callee": "any", "source_file": "backend/app/services/text_extractor.py", "source_location": "L136"}, {"caller_nid": "text_extractor_extract_xlsx", "callee": "strip", "source_file": "backend/app/services/text_extractor.py", "source_location": "L136"}, {"caller_nid": "text_extractor_extract_xlsx", "callee": "append", "source_file": "backend/app/services/text_extractor.py", "source_location": "L137"}, {"caller_nid": "text_extractor_extract_xlsx", "callee": "join", "source_file": "backend/app/services/text_extractor.py", "source_location": "L137"}, {"caller_nid": "text_extractor_extract_xlsx", "callee": "append", "source_file": "backend/app/services/text_extractor.py", "source_location": "L140"}, {"caller_nid": "text_extractor_extract_xlsx", "callee": "join", "source_file": "backend/app/services/text_extractor.py", "source_location": "L140"}, {"caller_nid": "text_extractor_extract_xlsx", "callee": "close", "source_file": "backend/app/services/text_extractor.py", "source_location": "L142"}, {"caller_nid": "text_extractor_extract_xlsx", "callee": "join", "source_file": "backend/app/services/text_extractor.py", "source_location": "L143"}, {"caller_nid": "text_extractor_extract_pptx", "callee": "Presentation", "source_file": "backend/app/services/text_extractor.py", "source_location": "L150"}, {"caller_nid": "text_extractor_extract_pptx", "callee": "BytesIO", "source_file": "backend/app/services/text_extractor.py", "source_location": "L150"}, {"caller_nid": "text_extractor_extract_pptx", "callee": "enumerate", "source_file": "backend/app/services/text_extractor.py", "source_location": "L153"}, {"caller_nid": "text_extractor_extract_pptx", "callee": "strip", "source_file": "backend/app/services/text_extractor.py", "source_location": "L158"}, {"caller_nid": "text_extractor_extract_pptx", "callee": "append", "source_file": "backend/app/services/text_extractor.py", "source_location": "L160"}, {"caller_nid": "text_extractor_extract_pptx", "callee": "strip", "source_file": "backend/app/services/text_extractor.py", "source_location": "L163"}, {"caller_nid": "text_extractor_extract_pptx", "callee": "append", "source_file": "backend/app/services/text_extractor.py", "source_location": "L164"}, {"caller_nid": "text_extractor_extract_pptx", "callee": "join", "source_file": "backend/app/services/text_extractor.py", "source_location": "L164"}, {"caller_nid": "text_extractor_extract_pptx", "callee": "append", "source_file": "backend/app/services/text_extractor.py", "source_location": "L167"}, {"caller_nid": "text_extractor_extract_pptx", "callee": "join", "source_file": "backend/app/services/text_extractor.py", "source_location": "L167"}, {"caller_nid": "text_extractor_extract_pptx", "callee": "join", "source_file": "backend/app/services/text_extractor.py", "source_location": "L169"}]}