{"nodes": [{"id": "backend_app_core_permissions_py", "label": "permissions.py", "file_type": "code", "source_file": "backend/app/core/permissions.py", "source_location": "L1"}, {"id": "permissions_check_agent_access", "label": "check_agent_access()", "file_type": "code", "source_file": "backend/app/core/permissions.py", "source_location": "L15"}, {"id": "permissions_is_agent_creator", "label": "is_agent_creator()", "file_type": "code", "source_file": "backend/app/core/permissions.py", "source_location": "L55"}, {"id": "permissions_is_agent_expired", "label": "is_agent_expired()", "file_type": "code", "source_file": "backend/app/core/permissions.py", "source_location": "L60"}, {"id": "permissions_rationale_1", "label": "RBAC permission checking utilities.", "file_type": "rationale", "source_file": "backend/app/core/permissions.py", "source_location": "L1"}, {"id": "permissions_rationale_16", "label": "Check if a user has access to a specific agent.      Returns (agent, access_leve", "file_type": "rationale", "source_file": "backend/app/core/permissions.py", "source_location": "L16"}, {"id": "permissions_rationale_56", "label": "Check if the user is the creator (admin) of the agent.", "file_type": "rationale", "source_file": "backend/app/core/permissions.py", "source_location": "L56"}, {"id": "permissions_rationale_61", "label": "Return True if the agent is manually marked expired or its expires_at is in the", "file_type": "rationale", "source_file": "backend/app/core/permissions.py", "source_location": "L61"}], "edges": [{"source": "backend_app_core_permissions_py", "target": "uuid", "relation": "imports", "confidence": "EXTRACTED", "source_file": "backend/app/core/permissions.py", "source_location": "L3", "weight": 1.0}, {"source": "backend_app_core_permissions_py", "target": "datetime", "relation": "imports_from", "confidence": "EXTRACTED", "source_file": "backend/app/core/permissions.py", "source_location": "L4", "weight": 1.0}, {"source": "backend_app_core_permissions_py", "target": "typing", "relation": "imports_from", "confidence": "EXTRACTED", "source_file": "backend/app/core/permissions.py", "source_location": "L5", "weight": 1.0}, {"source": "backend_app_core_permissions_py", "target": "fastapi", "relation": "imports_from", "confidence": "EXTRACTED", "source_file": "backend/app/core/permissions.py", "source_location": "L7", "weight": 1.0}, {"source": "backend_app_core_permissions_py", "target": "sqlalchemy", "relation": "imports_from", "confidence": "EXTRACTED", "source_file": "backend/app/core/permissions.py", "source_location": "L8", "weight": 1.0}, {"source": "backend_app_core_permissions_py", "target": "sqlalchemy_ext_asyncio", "relation": "imports_from", "confidence": "EXTRACTED", "source_file": "backend/app/core/permissions.py", "source_location": "L9", "weight": 1.0}, {"source": "backend_app_core_permissions_py", "target": "app_models_agent", "relation": "imports_from", "confidence": "EXTRACTED", "source_file": "backend/app/core/permissions.py", "source_location": "L11", "weight": 1.0}, {"source": "backend_app_core_permissions_py", "target": "app_models_user", "relation": "imports_from", "confidence": "EXTRACTED", "source_file": "backend/app/core/permissions.py", "source_location": "L12", "weight": 1.0}, {"source": "backend_app_core_permissions_py", "target": "permissions_check_agent_access", "relation": "contains", "confidence": "EXTRACTED", "source_file": "backend/app/core/permissions.py", "source_location": "L15", "weight": 1.0}, {"source": "backend_app_core_permissions_py", "target": "permissions_is_agent_creator", "relation": "contains", "confidence": "EXTRACTED", "source_file": "backend/app/core/permissions.py", "source_location": "L55", "weight": 1.0}, {"source": "backend_app_core_permissions_py", "target": "permissions_is_agent_expired", "relation": "contains", "confidence": "EXTRACTED", "source_file": "backend/app/core/permissions.py", "source_location": "L60", "weight": 1.0}, {"source": "permissions_rationale_1", "target": "backend_app_core_permissions_py", "relation": "rationale_for", "confidence": "EXTRACTED", "source_file": "backend/app/core/permissions.py", "source_location": "L1", "weight": 1.0}, {"source": "permissions_rationale_16", "target": "permissions_check_agent_access", "relation": "rationale_for", "confidence": "EXTRACTED", "source_file": "backend/app/core/permissions.py", "source_location": "L16", "weight": 1.0}, {"source": "permissions_rationale_56", "target": "permissions_is_agent_creator", "relation": "rationale_for", "confidence": "EXTRACTED", "source_file": "backend/app/core/permissions.py", "source_location": "L56", "weight": 1.0}, {"source": "permissions_rationale_61", "target": "permissions_is_agent_expired", "relation": "rationale_for", "confidence": "EXTRACTED", "source_file": "backend/app/core/permissions.py", "source_location": "L61", "weight": 1.0}], "raw_calls": [{"caller_nid": "permissions_check_agent_access", "callee": "execute", "source_file": "backend/app/core/permissions.py", "source_location": "L25"}, {"caller_nid": "permissions_check_agent_access", "callee": "where", "source_file": "backend/app/core/permissions.py", "source_location": "L25"}, {"caller_nid": "permissions_check_agent_access", "callee": "select", "source_file": "backend/app/core/permissions.py", "source_location": "L25"}, {"caller_nid": "permissions_check_agent_access", "callee": "scalar_one_or_none", "source_file": "backend/app/core/permissions.py", "source_location": "L26"}, {"caller_nid": "permissions_check_agent_access", "callee": "HTTPException", "source_file": "backend/app/core/permissions.py", "source_location": "L28"}, {"caller_nid": "permissions_check_agent_access", "callee": "HTTPException", "source_file": "backend/app/core/permissions.py", "source_location": "L36"}, {"caller_nid": "permissions_check_agent_access", "callee": "execute", "source_file": "backend/app/core/permissions.py", "source_location": "L43"}, {"caller_nid": "permissions_check_agent_access", "callee": "where", "source_file": "backend/app/core/permissions.py", "source_location": "L43"}, {"caller_nid": "permissions_check_agent_access", "callee": "select", "source_file": "backend/app/core/permissions.py", "source_location": "L43"}, {"caller_nid": "permissions_check_agent_access", "callee": "all", "source_file": "backend/app/core/permissions.py", "source_location": "L44"}, {"caller_nid": "permissions_check_agent_access", "callee": "scalars", "source_file": "backend/app/core/permissions.py", "source_location": "L44"}, {"caller_nid": "permissions_check_agent_access", "callee": "HTTPException", "source_file": "backend/app/core/permissions.py", "source_location": "L52"}, {"caller_nid": "permissions_is_agent_expired", "callee": "getattr", "source_file": "backend/app/core/permissions.py", "source_location": "L62"}, {"caller_nid": "permissions_is_agent_expired", "callee": "getattr", "source_file": "backend/app/core/permissions.py", "source_location": "L64"}, {"caller_nid": "permissions_is_agent_expired", "callee": "now", "source_file": "backend/app/core/permissions.py", "source_location": "L65"}]}