{"nodes": [{"id": "agents", "label": "agents.py", "file_type": "code", "source_file": "backend/app/plugins/clawith_acp/commands/agents.py", "source_location": "L1"}, {"id": "agents_agentscommand", "label": "AgentsCommand", "file_type": "code", "source_file": "backend/app/plugins/clawith_acp/commands/agents.py", "source_location": "L9"}, {"id": "acpcommand", "label": "AcpCommand", "file_type": "code", "source_file": "", "source_location": ""}, {"id": "agents_name", "label": "name()", "file_type": "code", "source_file": "backend/app/plugins/clawith_acp/commands/agents.py", "source_location": "L11"}, {"id": "agents_description", "label": "description()", "file_type": "code", "source_file": "backend/app/plugins/clawith_acp/commands/agents.py", "source_location": "L15"}, {"id": "agents_aliases", "label": "aliases()", "file_type": "code", "source_file": "backend/app/plugins/clawith_acp/commands/agents.py", "source_location": "L19"}, {"id": "agents_agentscommand_execute", "label": ".execute()", "file_type": "code", "source_file": "backend/app/plugins/clawith_acp/commands/agents.py", "source_location": "L22"}, {"id": "agents_rationale_1", "label": "agents command - list available agents for current tenant/user.", "file_type": "rationale", "source_file": "backend/app/plugins/clawith_acp/commands/agents.py", "source_location": "L1"}], "edges": [{"source": "agents", "target": "base", "relation": "imports_from", "confidence": "EXTRACTED", "source_file": "backend/app/plugins/clawith_acp/commands/agents.py", "source_location": "L2", "weight": 1.0}, {"source": "agents", "target": "sqlalchemy", "relation": "imports_from", "confidence": "EXTRACTED", "source_file": "backend/app/plugins/clawith_acp/commands/agents.py", "source_location": "L3", "weight": 1.0}, {"source": "agents", "target": "app_database", "relation": "imports_from", "confidence": "EXTRACTED", "source_file": "backend/app/plugins/clawith_acp/commands/agents.py", "source_location": "L4", "weight": 1.0}, {"source": "agents", "target": "app_models_agent", "relation": "imports_from", "confidence": "EXTRACTED", "source_file": "backend/app/plugins/clawith_acp/commands/agents.py", "source_location": "L5", "weight": 1.0}, {"source": "agents", "target": "app_models_user", "relation": "imports_from", "confidence": "EXTRACTED", "source_file": "backend/app/plugins/clawith_acp/commands/agents.py", "source_location": "L6", "weight": 1.0}, {"source": "agents", "target": "agents_agentscommand", "relation": "contains", "confidence": "EXTRACTED", "source_file": "backend/app/plugins/clawith_acp/commands/agents.py", "source_location": "L9", "weight": 1.0}, {"source": "agents_agentscommand", "target": "acpcommand", "relation": "inherits", "confidence": "EXTRACTED", "source_file": "backend/app/plugins/clawith_acp/commands/agents.py", "source_location": "L9", "weight": 1.0}, {"source": "agents", "target": "agents_name", "relation": "contains", "confidence": "EXTRACTED", "source_file": "backend/app/plugins/clawith_acp/commands/agents.py", "source_location": "L11", "weight": 1.0}, {"source": "agents", "target": "agents_description", "relation": "contains", "confidence": "EXTRACTED", "source_file": "backend/app/plugins/clawith_acp/commands/agents.py", "source_location": "L15", "weight": 1.0}, {"source": "agents", "target": "agents_aliases", "relation": "contains", "confidence": "EXTRACTED", "source_file": "backend/app/plugins/clawith_acp/commands/agents.py", "source_location": "L19", "weight": 1.0}, {"source": "agents_agentscommand", "target": "agents_agentscommand_execute", "relation": "method", "confidence": "EXTRACTED", "source_file": "backend/app/plugins/clawith_acp/commands/agents.py", "source_location": "L22", "weight": 1.0}, {"source": "agents_rationale_1", "target": "agents", "relation": "rationale_for", "confidence": "EXTRACTED", "source_file": "backend/app/plugins/clawith_acp/commands/agents.py", "source_location": "L1", "weight": 1.0}]}