{"nodes": [{"id": "platformdashboard", "label": "PlatformDashboard.tsx", "file_type": "code", "source_file": "frontend/src/pages/PlatformDashboard.tsx", "source_location": "L1"}, {"id": "platformdashboard_formattokens", "label": "formatTokens()", "file_type": "code", "source_file": "frontend/src/pages/PlatformDashboard.tsx", "source_location": "L11"}, {"id": "platformdashboard_formatnumber", "label": "formatNumber()", "file_type": "code", "source_file": "frontend/src/pages/PlatformDashboard.tsx", "source_location": "L19"}, {"id": "platformdashboard_infotooltip", "label": "InfoTooltip()", "file_type": "code", "source_file": "frontend/src/pages/PlatformDashboard.tsx", "source_location": "L37"}, {"id": "platformdashboard_metriccard", "label": "MetricCard()", "file_type": "code", "source_file": "frontend/src/pages/PlatformDashboard.tsx", "source_location": "L93"}, {"id": "platformdashboard_authheaders", "label": "authHeaders()", "file_type": "code", "source_file": "frontend/src/pages/PlatformDashboard.tsx", "source_location": "L139"}, {"id": "platformdashboard_fetchtimeseries", "label": "fetchTimeSeries()", "file_type": "code", "source_file": "frontend/src/pages/PlatformDashboard.tsx", "source_location": "L144"}, {"id": "platformdashboard_fetchleaderboards", "label": "fetchLeaderboards()", "file_type": "code", "source_file": "frontend/src/pages/PlatformDashboard.tsx", "source_location": "L159"}, {"id": "platformdashboard_fetchenhanced", "label": "fetchEnhanced()", "file_type": "code", "source_file": "frontend/src/pages/PlatformDashboard.tsx", "source_location": "L172"}], "edges": [{"source": "platformdashboard", "target": "react", "relation": "imports_from", "confidence": "EXTRACTED", "source_file": "frontend/src/pages/PlatformDashboard.tsx", "source_location": "L1", "weight": 1.0}, {"source": "platformdashboard", "target": "react_i18next", "relation": "imports_from", "confidence": "EXTRACTED", "source_file": "frontend/src/pages/PlatformDashboard.tsx", "source_location": "L2", "weight": 1.0}, {"source": "platformdashboard", "target": "recharts", "relation": "imports_from", "confidence": "EXTRACTED", "source_file": "frontend/src/pages/PlatformDashboard.tsx", "source_location": "L3", "weight": 1.0}, {"source": "platformdashboard", "target": "platformdashboard_formattokens", "relation": "contains", "confidence": "EXTRACTED", "source_file": "frontend/src/pages/PlatformDashboard.tsx", "source_location": "L11", "weight": 1.0}, {"source": "platformdashboard", "target": "platformdashboard_formatnumber", "relation": "contains", "confidence": "EXTRACTED", "source_file": "frontend/src/pages/PlatformDashboard.tsx", "source_location": "L19", "weight": 1.0}, {"source": "platformdashboard", "target": "platformdashboard_infotooltip", "relation": "contains", "confidence": "EXTRACTED", "source_file": "frontend/src/pages/PlatformDashboard.tsx", "source_location": "L37", "weight": 1.0}, {"source": "platformdashboard", "target": "platformdashboard_metriccard", "relation": "contains", "confidence": "EXTRACTED", "source_file": "frontend/src/pages/PlatformDashboard.tsx", "source_location": "L93", "weight": 1.0}, {"source": "platformdashboard", "target": "platformdashboard_authheaders", "relation": "contains", "confidence": "EXTRACTED", "source_file": "frontend/src/pages/PlatformDashboard.tsx", "source_location": "L139", "weight": 1.0}, {"source": "platformdashboard", "target": "platformdashboard_fetchtimeseries", "relation": "contains", "confidence": "EXTRACTED", "source_file": "frontend/src/pages/PlatformDashboard.tsx", "source_location": "L144", "weight": 1.0}, {"source": "platformdashboard", "target": "platformdashboard_fetchleaderboards", "relation": "contains", "confidence": "EXTRACTED", "source_file": "frontend/src/pages/PlatformDashboard.tsx", "source_location": "L159", "weight": 1.0}, {"source": "platformdashboard", "target": "platformdashboard_fetchenhanced", "relation": "contains", "confidence": "EXTRACTED", "source_file": "frontend/src/pages/PlatformDashboard.tsx", "source_location": "L172", "weight": 1.0}, {"source": "platformdashboard_fetchtimeseries", "target": "platformdashboard_authheaders", "relation": "calls", "confidence": "EXTRACTED", "source_file": "frontend/src/pages/PlatformDashboard.tsx", "source_location": "L152", "weight": 1.0}, {"source": "platformdashboard_fetchleaderboards", "target": "platformdashboard_authheaders", "relation": "calls", "confidence": "EXTRACTED", "source_file": "frontend/src/pages/PlatformDashboard.tsx", "source_location": "L162", "weight": 1.0}, {"source": "platformdashboard_fetchenhanced", "target": "platformdashboard_authheaders", "relation": "calls", "confidence": "EXTRACTED", "source_file": "frontend/src/pages/PlatformDashboard.tsx", "source_location": "L175", "weight": 1.0}], "hyperedges": []}