{"nodes": [{"id": "relationships", "label": "relationships.py", "file_type": "code", "source_file": "backend/app/api/relationships.py", "source_location": "L1"}, {"id": "relationships_relationshipin", "label": "RelationshipIn", "file_type": "code", "source_file": "backend/app/api/relationships.py", "source_location": "L44"}, {"id": "relationships_relationshipbatchin", "label": "RelationshipBatchIn", "file_type": "code", "source_file": "backend/app/api/relationships.py", "source_location": "L50"}, {"id": "relationships_agentrelationshipin", "label": "AgentRelationshipIn", "file_type": "code", "source_file": "backend/app/api/relationships.py", "source_location": "L54"}, {"id": "relationships_agentrelationshipbatchin", "label": "AgentRelationshipBatchIn", "file_type": "code", "source_file": "backend/app/api/relationships.py", "source_location": "L60"}, {"id": "relationships_get_relationships", "label": "get_relationships()", "file_type": "code", "source_file": "backend/app/api/relationships.py", "source_location": "L67"}, {"id": "relationships_save_relationships", "label": "save_relationships()", "file_type": "code", "source_file": "backend/app/api/relationships.py", "source_location": "L103"}, {"id": "relationships_delete_relationship", "label": "delete_relationship()", "file_type": "code", "source_file": "backend/app/api/relationships.py", "source_location": "L133"}, {"id": "relationships_get_agent_relationships", "label": "get_agent_relationships()", "file_type": "code", "source_file": "backend/app/api/relationships.py", "source_location": "L157"}, {"id": "relationships_save_agent_relationships", "label": "save_agent_relationships()", "file_type": "code", "source_file": "backend/app/api/relationships.py", "source_location": "L189"}, {"id": "relationships_delete_agent_relationship", "label": "delete_agent_relationship()", "file_type": "code", "source_file": "backend/app/api/relationships.py", "source_location": "L220"}, {"id": "relationships_regenerate_relationships_file", "label": "_regenerate_relationships_file()", "file_type": "code", "source_file": "backend/app/api/relationships.py", "source_location": "L246"}, {"id": "relationships_rationale_1", "label": "Agent relationship management API \u2014 human + agent-to-agent.", "file_type": "rationale", "source_file": "backend/app/api/relationships.py", "source_location": "L1"}, {"id": "relationships_rationale_72", "label": "Get all human relationships for this agent.", "file_type": "rationale", "source_file": "backend/app/api/relationships.py", "source_location": "L72"}, {"id": "relationships_rationale_109", "label": "Replace all human relationships for this agent.", "file_type": "rationale", "source_file": "backend/app/api/relationships.py", "source_location": "L109"}, {"id": "relationships_rationale_139", "label": "Delete a single human relationship.", "file_type": "rationale", "source_file": "backend/app/api/relationships.py", "source_location": "L139"}, {"id": "relationships_rationale_162", "label": "Get all agent-to-agent relationships.", "file_type": "rationale", "source_file": "backend/app/api/relationships.py", "source_location": "L162"}, {"id": "relationships_rationale_195", "label": "Replace all agent-to-agent relationships.", "file_type": "rationale", "source_file": "backend/app/api/relationships.py", "source_location": "L195"}, {"id": "relationships_rationale_226", "label": "Delete a single agent-to-agent relationship.", "file_type": "rationale", "source_file": "backend/app/api/relationships.py", "source_location": "L226"}, {"id": "relationships_rationale_247", "label": "Regenerate relationships.md with both human and agent relationships.", "file_type": "rationale", "source_file": "backend/app/api/relationships.py", "source_location": "L247"}], "edges": [{"source": "relationships", "target": "json", "relation": "imports", "confidence": "EXTRACTED", "source_file": "backend/app/api/relationships.py", "source_location": "L3", "weight": 1.0}, {"source": "relationships", "target": "uuid", "relation": "imports", "confidence": "EXTRACTED", "source_file": "backend/app/api/relationships.py", "source_location": "L4", "weight": 1.0}, {"source": "relationships", "target": "pathlib", "relation": "imports_from", "confidence": "EXTRACTED", "source_file": "backend/app/api/relationships.py", "source_location": "L5", "weight": 1.0}, {"source": "relationships", "target": "fastapi", "relation": "imports_from", "confidence": "EXTRACTED", "source_file": "backend/app/api/relationships.py", "source_location": "L7", "weight": 1.0}, {"source": "relationships", "target": "pydantic", "relation": "imports_from", "confidence": "EXTRACTED", "source_file": "backend/app/api/relationships.py", "source_location": "L8", "weight": 1.0}, {"source": "relationships", "target": "sqlalchemy", "relation": "imports_from", "confidence": "EXTRACTED", "source_file": "backend/app/api/relationships.py", "source_location": "L9", "weight": 1.0}, {"source": "relationships", "target": "sqlalchemy_ext_asyncio", "relation": "imports_from", "confidence": "EXTRACTED", "source_file": "backend/app/api/relationships.py", "source_location": "L10", "weight": 1.0}, {"source": "relationships", "target": "sqlalchemy_orm", "relation": "imports_from", "confidence": "EXTRACTED", "source_file": "backend/app/api/relationships.py", "source_location": "L11", "weight": 1.0}, {"source": "relationships", "target": "app_config", "relation": "imports_from", "confidence": "EXTRACTED", "source_file": "backend/app/api/relationships.py", "source_location": "L13", "weight": 1.0}, {"source": "relationships", "target": "app_core_security", "relation": "imports_from", "confidence": "EXTRACTED", "source_file": "backend/app/api/relationships.py", "source_location": "L14", "weight": 1.0}, {"source": "relationships", "target": "app_core_permissions", "relation": "imports_from", "confidence": "EXTRACTED", "source_file": "backend/app/api/relationships.py", "source_location": "L15", "weight": 1.0}, {"source": "relationships", "target": "app_database", "relation": "imports_from", "confidence": "EXTRACTED", "source_file": "backend/app/api/relationships.py", "source_location": "L16", "weight": 1.0}, {"source": "relationships", "target": "app_models_org", "relation": "imports_from", "confidence": "EXTRACTED", "source_file": "backend/app/api/relationships.py", "source_location": "L17", "weight": 1.0}, {"source": "relationships", "target": "app_models_user", "relation": "imports_from", "confidence": "EXTRACTED", "source_file": "backend/app/api/relationships.py", "source_location": "L18", "weight": 1.0}, {"source": "relationships", "target": "relationships_relationshipin", "relation": "contains", "confidence": "EXTRACTED", "source_file": "backend/app/api/relationships.py", "source_location": "L44", "weight": 1.0}, {"source": "relationships_relationshipin", "target": "basemodel", "relation": "inherits", "confidence": "EXTRACTED", "source_file": "backend/app/api/relationships.py", "source_location": "L44", "weight": 1.0}, {"source": "relationships", "target": "relationships_relationshipbatchin", "relation": "contains", "confidence": "EXTRACTED", "source_file": "backend/app/api/relationships.py", "source_location": "L50", "weight": 1.0}, {"source": "relationships_relationshipbatchin", "target": "basemodel", "relation": "inherits", "confidence": "EXTRACTED", "source_file": "backend/app/api/relationships.py", "source_location": "L50", "weight": 1.0}, {"source": "relationships", "target": "relationships_agentrelationshipin", "relation": "contains", "confidence": "EXTRACTED", "source_file": "backend/app/api/relationships.py", "source_location": "L54", "weight": 1.0}, {"source": "relationships_agentrelationshipin", "target": "basemodel", "relation": "inherits", "confidence": "EXTRACTED", "source_file": "backend/app/api/relationships.py", "source_location": "L54", "weight": 1.0}, {"source": "relationships", "target": "relationships_agentrelationshipbatchin", "relation": "contains", "confidence": "EXTRACTED", "source_file": "backend/app/api/relationships.py", "source_location": "L60", "weight": 1.0}, {"source": "relationships_agentrelationshipbatchin", "target": "basemodel", "relation": "inherits", "confidence": "EXTRACTED", "source_file": "backend/app/api/relationships.py", "source_location": "L60", "weight": 1.0}, {"source": "relationships", "target": "relationships_get_relationships", "relation": "contains", "confidence": "EXTRACTED", "source_file": "backend/app/api/relationships.py", "source_location": "L67", "weight": 1.0}, {"source": "relationships", "target": "relationships_save_relationships", "relation": "contains", "confidence": "EXTRACTED", "source_file": "backend/app/api/relationships.py", "source_location": "L103", "weight": 1.0}, {"source": "relationships", "target": "relationships_delete_relationship", "relation": "contains", "confidence": "EXTRACTED", "source_file": "backend/app/api/relationships.py", "source_location": "L133", "weight": 1.0}, {"source": "relationships", "target": "relationships_get_agent_relationships", "relation": "contains", "confidence": "EXTRACTED", "source_file": "backend/app/api/relationships.py", "source_location": "L157", "weight": 1.0}, {"source": "relationships", "target": "relationships_save_agent_relationships", "relation": "contains", "confidence": "EXTRACTED", "source_file": "backend/app/api/relationships.py", "source_location": "L189", "weight": 1.0}, {"source": "relationships", "target": "relationships_delete_agent_relationship", "relation": "contains", "confidence": "EXTRACTED", "source_file": "backend/app/api/relationships.py", "source_location": "L220", "weight": 1.0}, {"source": "relationships", "target": "relationships_regenerate_relationships_file", "relation": "contains", "confidence": "EXTRACTED", "source_file": "backend/app/api/relationships.py", "source_location": "L246", "weight": 1.0}, {"source": "relationships_save_relationships", "target": "relationships_regenerate_relationships_file", "relation": "calls", "confidence": "EXTRACTED", "source_file": "backend/app/api/relationships.py", "source_location": "L127", "weight": 1.0}, {"source": "relationships_delete_relationship", "target": "relationships_regenerate_relationships_file", "relation": "calls", "confidence": "EXTRACTED", "source_file": "backend/app/api/relationships.py", "source_location": "L148", "weight": 1.0}, {"source": "relationships_save_agent_relationships", "target": "relationships_regenerate_relationships_file", "relation": "calls", "confidence": "EXTRACTED", "source_file": "backend/app/api/relationships.py", "source_location": "L214", "weight": 1.0}, {"source": "relationships_delete_agent_relationship", "target": "relationships_regenerate_relationships_file", "relation": "calls", "confidence": "EXTRACTED", "source_file": "backend/app/api/relationships.py", "source_location": "L238", "weight": 1.0}, {"source": "relationships_rationale_1", "target": "relationships", "relation": "rationale_for", "confidence": "EXTRACTED", "source_file": "backend/app/api/relationships.py", "source_location": "L1", "weight": 1.0}, {"source": "relationships_rationale_72", "target": "relationships_get_relationships", "relation": "rationale_for", "confidence": "EXTRACTED", "source_file": "backend/app/api/relationships.py", "source_location": "L72", "weight": 1.0}, {"source": "relationships_rationale_109", "target": "relationships_save_relationships", "relation": "rationale_for", "confidence": "EXTRACTED", "source_file": "backend/app/api/relationships.py", "source_location": "L109", "weight": 1.0}, {"source": "relationships_rationale_139", "target": "relationships_delete_relationship", "relation": "rationale_for", "confidence": "EXTRACTED", "source_file": "backend/app/api/relationships.py", "source_location": "L139", "weight": 1.0}, {"source": "relationships_rationale_162", "target": "relationships_get_agent_relationships", "relation": "rationale_for", "confidence": "EXTRACTED", "source_file": "backend/app/api/relationships.py", "source_location": "L162", "weight": 1.0}, {"source": "relationships_rationale_195", "target": "relationships_save_agent_relationships", "relation": "rationale_for", "confidence": "EXTRACTED", "source_file": "backend/app/api/relationships.py", "source_location": "L195", "weight": 1.0}, {"source": "relationships_rationale_226", "target": "relationships_delete_agent_relationship", "relation": "rationale_for", "confidence": "EXTRACTED", "source_file": "backend/app/api/relationships.py", "source_location": "L226", "weight": 1.0}, {"source": "relationships_rationale_247", "target": "relationships_regenerate_relationships_file", "relation": "rationale_for", "confidence": "EXTRACTED", "source_file": "backend/app/api/relationships.py", "source_location": "L247", "weight": 1.0}], "hyperedges": []}